pytorch_to_tflite/__init__.py
pytorch_to_tflite/_nbdev.py
pytorch_to_tflite/pytorch_to_tflite.py
pytorch_to_tflite-0.0.4.dist-info/LICENSE
pytorch_to_tflite-0.0.4.dist-info/METADATA
pytorch_to_tflite-0.0.4.dist-info/WHEEL
pytorch_to_tflite-0.0.4.dist-info/entry_points.txt
pytorch_to_tflite-0.0.4.dist-info/top_level.txt
pytorch_to_tflite-0.0.4.dist-info/RECORD
