Metadata-Version: 2.1
Name: pytorch-to-tflite
Version: 0.0.4
Summary: Convert deep learning models
Home-page: https://github.com/anhvth/pytorch_to_tflite/tree/main/
Author: Anh Vo Tran Hai
Author-email: anhvth.226@gmail.com
License: Apache Software License 2.0
Keywords: pytorch to tflite
Platform: UNKNOWN
Classifier: Development Status :: 3 - Alpha
Classifier: Intended Audience :: Developers
Classifier: Natural Language :: English
Classifier: Programming Language :: Python :: 3.6
Classifier: Programming Language :: Python :: 3.7
Classifier: Programming Language :: Python :: 3.8
Classifier: License :: OSI Approved :: Apache Software License
Requires-Python: >=3.6
Requires-Dist: pip
Requires-Dist: packaging
Requires-Dist: onnx
Requires-Dist: pytorch
Requires-Dist: tensorflow
Provides-Extra: dev
